README.rst
setup.py
pip_module/__init__.py
pip_module/__main__.py
pip_module/awesome_module.py
pip_module.egg-info/PKG-INFO
pip_module.egg-info/SOURCES.txt
pip_module.egg-info/dependency_links.txt
pip_module.egg-info/entry_points.txt
pip_module.egg-info/top_level.txt